Workbook
Name Slicer_Invoice_Date__Year: #N/A
Name Slicer_Region: #N/A

Sheet Data
B2: Retailer Dataset
B4: Retailer | C4: Retailer ID | D4: Invoice Date | E4: Region | F4: State | G4: City | H4: Beverage Brand | I4: Price per Unit | J4: Units Sold | K4: Total Sales | L4: Operating Profit | M4: Operating Margin | N4: Year | O4: Month | P4: Quarter
B5: BevCo | C5: 1185732 | D5: 44562 | E5: Northeast | F5: New York | G5: New York | H5: Coca-Cola | I5: 0.5 | J5: 12000 | K5: 6000 | L5: 3000 | M5: 0.5 | N5: =YEAR(D5) -> 2022 | O5: =MONTH(D5) -> 1 | P5: ="Q"&ROUNDUP(MONTH(D5)/3,0) -> Q1
B6: BevCo | C6: 1185732 | D6: 44563 | E6: Northeast | F6: New York | G6: New York | H6: Diet Coke | I6: 0.5 | J6: 10000 | K6: 5000 | L6: 1500 | M6: 0.3 | N6: =YEAR(D6) -> 2022 | O6: =MONTH(D6) -> 1 | P6: ="Q"&ROUNDUP(MONTH(D6)/3,0) -> Q1
B7: BevCo | C7: 1185732 | D7: 44564 | E7: Northeast | F7: New York | G7: New York | H7: Sprite | I7: 0.4 | J7: 10000 | K7: 4000 | L7: 1400 | M7: 0.35 | N7: =YEAR(D7) -> 2022 | O7: =MONTH(D7) -> 1 | P7: ="Q"&ROUNDUP(MONTH(D7)/3,0) -> Q1
B8: BevCo | C8: 1185732 | D8: 44565 | E8: Northeast | F8: New York | G8: New York | H8: Fanta | I8: 0.45 | J8: 8500 | K8: 3825 | L8: 1338.75 | M8: 0.35 | N8: =YEAR(D8) -> 2022 | O8: =MONTH(D8) -> 1 | P8: ="Q"&ROUNDUP(MONTH(D8)/3,0) -> Q1
B9: BevCo | C9: 1185732 | D9: 44566 | E9: Northeast | F9: New York | G9: New York | H9: Powerade | I9: 0.6 | J9: 9000 | K9: 5400 | L9: 1620 | M9: 0.3 | N9: =YEAR(D9) -> 2022 | O9: =MONTH(D9) -> 1 | P9: ="Q"&ROUNDUP(MONTH(D9)/3,0) -> Q1
B10: BevCo | C10: 1185732 | D10: 44567 | E10: Northeast | F10: New York | G10: New York | H10: Dasani Water | I10: 0.5 | J10: 10000 | K10: 5000 | L10: 1250 | M10: 0.25 | N10: =YEAR(D10) -> 2022 | O10: =MONTH(D10) -> 1 | P10: ="Q"&ROUNDUP(MONTH(D10)/3,0) -> Q1
B11: BevCo | C11: 1185732 | D11: 44568 | E11: Northeast | F11: New York | G11: New York | H11: Coca-Cola | I11: 0.5 | J11: 12500 | K11: 6250 | L11: 3125 | M11: 0.5 | N11: =YEAR(D11) -> 2022 | O11: =MONTH(D11) -> 1 | P11: ="Q"&ROUNDUP(MONTH(D11)/3,0) -> Q1
B12: BevCo | C12: 1185732 | D12: 44569 | E12: Northeast | F12: New York | G12: New York | H12: Diet Coke | I12: 0.5 | J12: 9000 | K12: 4500 | L12: 1350 | M12: 0.3 | N12: =YEAR(D12) -> 2022 | O12: =MONTH(D12) -> 1 | P12: ="Q"&ROUNDUP(MONTH(D12)/3,0) -> Q1
B13: BevCo | C13: 1185732 | D13: 44582 | E13: Northeast | F13: New York | G13: New York | H13: Sprite | I13: 0.4 | J13: 9500 | K13: 3800 | L13: 1330 | M13: 0.35 | N13: =YEAR(D13) -> 2022 | O13: =MONTH(D13) -> 1 | P13: ="Q"&ROUNDUP(MONTH(D13)/3,0) -> Q1
B14: BevCo | C14: 1185732 | D14: 44583 | E14: Northeast | F14: New York | G14: New York | H14: Fanta | I14: 0.45 | J14: 8250 | K14: 3712.5 | L14: 1299.375 | M14: 0.35 | N14: =YEAR(D14) -> 2022 | O14: =MONTH(D14) -> 1 | P14: ="Q"&ROUNDUP(MONTH(D14)/3,0) -> Q1
B15: BevCo | C15: 1185732 | D15: 44584 | E15: Northeast | F15: New York | G15: New York | H15: Powerade | I15: 0.6 | J15: 9000 | K15: 5400 | L15: 1620 | M15: 0.3 | N15: =YEAR(D15) -> 2022 | O15: =MONTH(D15) -> 1 | P15: ="Q"&ROUNDUP(MONTH(D15)/3,0) -> Q1
B16: BevCo | C16: 1185732 | D16: 44585 | E16: Northeast | F16: New York | G16: New York | H16: Dasani Water | I16: 0.5 | J16: 10000 | K16: 5000 | L16: 1250 | M16: 0.25 | N16: =YEAR(D16) -> 2022 | O16: =MONTH(D16) -> 1 | P16: ="Q"&ROUNDUP(MONTH(D16)/3,0) -> Q1
... B9652: BevCo | C9652: 1185732 | D9652: 44979 | E9652: Northeast | F9652: New Hampshire | G9652: Manchester | H9652: Sprite | I9652: 0.29 | J9652: 830 | K9652: 240.7 | L9652: 64.989 | M9652: 0.27 | N9652: =YEAR(D9652) -> 2023 | O9652: =MONTH(D9652) -> 2 | P9652: ="Q"&ROUNDUP(MONTH(D9652)/3,0) -> Q1

Sheet Analyze
B2: Sum of Total Sales | C2: Sum of Operating Profit | D2: Sum of Units Sold | E2: Average of Price per Unit
B3: 12016665 | C3: 4722496.8 | D3: 24788610 | E3: 0.45216625
B6: Sum of Total Sales | C6: Column Labels
B7: Row Labels | C7: 2022 | D7: 2023
B8: Coca-Cola | C8: 499102 | D8: 2268974.9
B9: Dasani Water | C9: 469270.7 | D9: 1917827.8
B10: Diet Coke | C10: 423758.7 | D10: 1633959.3
B11: Fanta | C11: 315489.2 | D11: 1116062.9
B12: Powerade | C12: 349533.9 | D12: 1302529.3
B13: Sprite | C13: 366578 | D13: 1353578.3
B14: Grand Total | C14: 2423732.5 | D14: 9592932.5
B16: Sum of Total Sales | C16: Column Labels
B17: Row Labels | C17: 2022 | D17: 2023
B18: Amazon | C18: 276210 | D18: 1009698.7
B19: BevCo | C19: 466788 | D19: 2327606.5
B20: FizzyCo | C20: 161210.1 | D20: 2262827.1
B21: Target | C21: 9250.3 | D21: 1341995
B22: Walmart | C22: 339912.5 | D22: 580211
B23: West Soda | C23: 1170361.6 | D23: 2070594.2
B24: Grand Total | C24: 2423732.5 | D24: 9592932.5
B27: Invoice Date (Year) | C27: Invoice Date (Quarter) | D27: Sum of Total Sales | E27: Average of Operating Margin
B28: 2022 | C28: Qtr1 | D28: 692776.1 | E28: 0.40174684 | G28: =B28 -> 2022 | H28: =C28 -> Qtr1 | I28: =D28 -> 692776.1 | J28: =E28 -> 0.40174684
C29: Qtr2 | D29: 644203.9 | E29: 0.4 | H29: =C29 -> Qtr2 | I29: =D29 -> 644203.9 | J29: =E29 -> 0.4
C30: Qtr3 | D30: 719170.4 | E30: 0.41026549 | H30: =C30 -> Qtr3 | I30: =D30 -> 719170.4 | J30: =E30 -> 0.41026549
C31: Qtr4 | D31: 367582.1 | E31: 0.40243816 | H31: =C31 -> Qtr4 | I31: =D31 -> 367582.1 | J31: =E31 -> 0.40243816
B32: 2023 | C32: Qtr1 | D32: 1877584.3 | E32: 0.41657045 | G32: =B32 -> 2023 | H32: =C32 -> Qtr1 | I32: =D32 -> 1877584.3 | J32: =E32 -> 0.41657045
C33: Qtr2 | D33: 2379424.8 | E33: 0.42755819 | H33: =C33 -> Qtr2 | I33: =D33 -> 2379424.8 | J33: =E33 -> 0.42755819
C34: Qtr3 | D34: 2805752.5 | E34: 0.4347017 | H34: =C34 -> Qtr3 | I34: =D34 -> 2805752.5 | J34: =E34 -> 0.4347017
C35: Qtr4 | D35: 2530170.9 | E35: 0.42483933 | H35: =C35 -> Qtr4 | I35: =D35 -> 2530170.9 | J35: =E35 -> 0.42483933
B36: Grand Total | D36: 12016665 | E36: 0.42299129
G38: =B36 -> Grand Total | I38: =D36 -> 12016665 | J38: =E36 -> 0.42299129

Sheet Dashboard
D10: Sales by Brands | I10: Sales by Retailers
D11: Brands | E11: Sales 2022 | F11: Sales 2023 | G11: Variance | I11: Retailers | J11: Sales 2022 | K11: Sales 2023 | L11: Variance
D12: =Analyze!B8 -> Coca-Cola | E12: =Analyze!C8 -> 499102 | F12: =Analyze!D8 -> 2268974.9 | G12: =F12-E12 -> 1769872.9 | I12: =Analyze!B18 -> Amazon | J12: =Analyze!C18 -> 276210 | K12: =Analyze!D18 -> 1009698.7 | L12: =K12-J12 -> 733488.7
D13: =Analyze!B9 -> Dasani Water | E13: =Analyze!C9 -> 469270.7 | F13: =Analyze!D9 -> 1917827.8 | G13: =F13-E13 -> 1448557.1 | I13: =Analyze!B19 -> BevCo | J13: =Analyze!C19 -> 466788 | K13: =Analyze!D19 -> 2327606.5 | L13: =K13-J13 -> 1860818.5
D14: =Analyze!B10 -> Diet Coke | E14: =Analyze!C10 -> 423758.7 | F14: =Analyze!D10 -> 1633959.3 | G14: =F14-E14 -> 1210200.6 | I14: =Analyze!B20 -> FizzyCo | J14: =Analyze!C20 -> 161210.1 | K14: =Analyze!D20 -> 2262827.1 | L14: =K14-J14 -> 2101617
D15: =Analyze!B11 -> Fanta | E15: =Analyze!C11 -> 315489.2 | F15: =Analyze!D11 -> 1116062.9 | G15: =F15-E15 -> 800573.7 | I15: =Analyze!B21 -> Target | J15: =Analyze!C21 -> 9250.3 | K15: =Analyze!D21 -> 1341995 | L15: =K15-J15 -> 1332744.7
D16: =Analyze!B12 -> Powerade | E16: =Analyze!C12 -> 349533.9 | F16: =Analyze!D12 -> 1302529.3 | G16: =F16-E16 -> 952995.4 | I16: =Analyze!B22 -> Walmart | J16: =Analyze!C22 -> 339912.5 | K16: =Analyze!D22 -> 580211 | L16: =K16-J16 -> 240298.5
D17: =Analyze!B13 -> Sprite | E17: =Analyze!C13 -> 366578 | F17: =Analyze!D13 -> 1353578.3 | G17: =F17-E17 -> 987000.3 | I17: =Analyze!B23 -> West Soda | J17: =Analyze!C23 -> 1170361.6 | K17: =Analyze!D23 -> 2070594.2 | L17: =K17-J17 -> 900232.6
D18: =Analyze!B14 -> Grand Total | E18: =SUM(E12:E17) -> 2423732.5 | F18: =SUM(F12:F17) -> 9592932.5 | G18: =F18-E18 -> 7169200 | I18: =Analyze!B24 -> Grand Total | J18: =SUM(J12:J17) -> 2423732.5 | K18: =SUM(K12:K17) -> 9592932.5 | L18: =K18-J18 -> 7169200
D20: Sales and Operating Profit Margin by Quarter
